gettopology/__init__.py
gettopology/azure_auth.py
gettopology/azure_service.py
gettopology/diagram_config.yaml
gettopology/diagram_generator.py
gettopology/main.py
gettopology/models.py
gettopology/utils.py
gettopology/diagram/__init__.py
gettopology/diagram/categorization.py
gettopology/diagram/config.py
gettopology/diagram/layout.py
gettopology/diagram/legend.py
gettopology/diagram/models.py
gettopology/diagram/connections/__init__.py
gettopology/diagram/connections/base.py
gettopology/diagram/connections/external.py
gettopology/diagram/connections/hub_to_hub.py
gettopology/diagram/connections/hub_to_spoke.py
gettopology/diagram/connections/hubless.py
gettopology/diagram/elements/__init__.py
gettopology/diagram/elements/edge_elements.py
gettopology/diagram/elements/vnet_elements.py
gettopology/diagram/pages/__init__.py
gettopology/diagram/pages/hubless_page.py
gettopology/diagram/pages/hybrid_page.py
gettopology/diagram/pages/main_page.py
gettopology/diagram/pages/orphan_page.py
gettopology-0.1.0a10.dist-info/licenses/LICENSE
gettopology-0.1.0a10.dist-info/METADATA
gettopology-0.1.0a10.dist-info/WHEEL
gettopology-0.1.0a10.dist-info/entry_points.txt
gettopology-0.1.0a10.dist-info/top_level.txt
gettopology-0.1.0a10.dist-info/RECORD
