Metadata-Version: 2.4
Name: gettopology
Version: 0.1.0a10
Summary: CLI tool for generating Azure VNet topology diagrams with enhanced features
Author-email: Panda <pandaeatsbamboomailer@pm.me>
License-Expression: MIT
Project-URL: Homepage, https://www.pandaeatsbamboo.com
Project-URL: Documentation, https://github.com/PandaEatsBambooBlog
Project-URL: Repository, https://github.com/PandaEatsBambooBlog
Project-URL: Issues, https://github.com/PandaEatsBambooBlog
Keywords: azure,networking,vnet,topology,diagram,drawio,cloud
Classifier: Development Status :: 3 - Alpha
Classifier: Intended Audience :: Developers
Classifier: Intended Audience :: System Administrators
Classifier: Operating System :: OS Independent
Classifier: Programming Language :: Python :: 3
Classifier: Programming Language :: Python :: 3.10
Classifier: Programming Language :: Python :: 3.11
Classifier: Programming Language :: Python :: 3.12
Classifier: Programming Language :: Python :: 3.13
Classifier: Topic :: System :: Networking
Classifier: Topic :: Utilities
Requires-Python: >=3.10
License-File: LICENSE
Requires-Dist: rich>=13.0.0
Requires-Dist: pydantic>=2.0.0
Requires-Dist: azure-identity>=1.25.1
Requires-Dist: azure-mgmt-resource>=24.0.0
Requires-Dist: azure-mgmt-network>=30.1.0
Requires-Dist: azure-mgmt-resourcegraph>=8.0.1
Requires-Dist: azure-mgmt-authorization>=4.0.0
Requires-Dist: pyyaml>=6.0.0
Requires-Dist: python-dotenv>=1.0.0
Requires-Dist: defusedxml>=0.7.1
Provides-Extra: dev
Requires-Dist: pytest>=7.0.0; extra == "dev"
Requires-Dist: pytest-cov>=4.0.0; extra == "dev"
Requires-Dist: ruff>=0.14.10; extra == "dev"
Requires-Dist: mypy>=1.19.1; extra == "dev"
Requires-Dist: bandit>=1.9.2; extra == "dev"
Dynamic: license-file
